terminal_chatgpt/__init__.py
terminal_chatgpt/core.py
terminal_chatgpt/gpt.py
terminal_chatgpt/spinner.py
terminal_chatgpt-0.0.4.dist-info/entry_points.txt
terminal_chatgpt-0.0.4.dist-info/WHEEL
terminal_chatgpt-0.0.4.dist-info/METADATA
terminal_chatgpt-0.0.4.dist-info/RECORD
