Metadata-Version: 2.1
Name: terminal-chatgpt
Version: 0.0.4
Summary: 
Author: Danylo Omelchenko
Author-email: dpixelstudio@gmail.com
Requires-Python: >=3.9,<4.0
Classifier: Programming Language :: Python :: 3
Classifier: Programming Language :: Python :: 3.9
Requires-Dist: click (==8.1.3)
Requires-Dist: halo (==0.0.31)
Requires-Dist: openai (==0.27.2)
Requires-Dist: prompt-toolkit (>=3.0.38,<4.0.0)
Requires-Dist: pyreadline (==2.1)
Requires-Dist: rich (==13.3.3)
